django_gitlab
